games/__init__.py
games/amazons.py
games/battleship.py
games/checkers.py
games/chess.py
games/connect4.py
games/dots_and_boxes.py
games/game.py
games/gomoku.py
games/king_of_the_hill_chess.py
games/monster_chess.py
games/multi_tic_tac_toe.py
games/othello.py
games/tic_tac_toe.py
heuristics/__init__.py
heuristics/network.py
heuristics/proxy_network.py
heuristics/utils.py
learning/__init__.py
learning/learning.py
learning/utils.py
move_selection/__init__.py
move_selection/mini_max.py
move_selection/move_chooser.py
move_selection/random_chooser.py
move_selection/raw_network.py
move_selection/tablebase_chooser.py
move_selection/iterative_deepening/__init__.py
move_selection/iterative_deepening/async_iterative_deepening.py
move_selection/iterative_deepening/deepening_node.py
move_selection/iterative_deepening/iterative_deepening.py
move_selection/mcts/__init__.py
move_selection/mcts/abstract_node.py
move_selection/mcts/async_mcts.py
move_selection/mcts/heuristic_node.py
move_selection/mcts/mcts.py
move_selection/mcts/rollout_node.py
perfect_information_game/__init__.py
perfect_information_game/games/__init__.py
perfect_information_game/games/amazons.py
perfect_information_game/games/battleship.py
perfect_information_game/games/checkers.py
perfect_information_game/games/chess.py
perfect_information_game/games/connect4.py
perfect_information_game/games/dots_and_boxes.py
perfect_information_game/games/game.py
perfect_information_game/games/gomoku.py
perfect_information_game/games/king_of_the_hill_chess.py
perfect_information_game/games/monster_chess.py
perfect_information_game/games/multi_tic_tac_toe.py
perfect_information_game/games/othello.py
perfect_information_game/games/tic_tac_toe.py
perfect_information_game/heuristics/__init__.py
perfect_information_game/heuristics/network.py
perfect_information_game/heuristics/proxy_network.py
perfect_information_game/heuristics/utils.py
perfect_information_game/learning/__init__.py
perfect_information_game/learning/learning.py
perfect_information_game-0.0.11.dist-info/LICENSE.txt
perfect_information_game-0.0.11.dist-info/METADATA
perfect_information_game-0.0.11.dist-info/WHEEL
perfect_information_game-0.0.11.dist-info/top_level.txt
perfect_information_game-0.0.11.dist-info/RECORD
