Metadata-Version: 2.1
Name: perfect-information-game
Version: 0.0.11
Summary: Create 2D perfect information board games, and play them with machine learning systems.
Home-page: https://github.com/amaarquadri/perfect-information-game
Author: Amaar Quadri
Author-email: amaarquadri@gmail.com
License: MIT
Platform: UNKNOWN
Classifier: License :: OSI Approved :: MIT License
Classifier: Programming Language :: Python :: 3
Classifier: Programming Language :: Python :: 3.8
Classifier: Operating System :: OS Independent
Requires-Python: >=3.8
Requires-Dist: numpy
Requires-Dist: tensorflow
Requires-Dist: tensorflowjs
Requires-Dist: keras
Requires-Dist: pygame
Requires-Dist: easygui
Provides-Extra: dev
Requires-Dist: chess ; extra == 'dev'
Requires-Dist: memory-profiler ; extra == 'dev'
Requires-Dist: matplotlib ; extra == 'dev'
Requires-Dist: check-manifest ; extra == 'dev'
Requires-Dist: twine ; extra == 'dev'
